LICENSE
README.md
setup.py
src/Retica/Plugin.py
src/Retica/Render.py
src/Retica/Request.py
src/Retica/Response.py
src/Retica/Sockets.py
src/Retica/Worker.py
src/Retica/__init__.py
src/Retica.egg-info/PKG-INFO
src/Retica.egg-info/SOURCES.txt
src/Retica.egg-info/dependency_links.txt
src/Retica.egg-info/entry_points.txt
src/Retica.egg-info/requires.txt
src/Retica.egg-info/top_level.txt
src/Retica/cli/__init__.py
src/Retica/cli/create.py
src/Retica/cli/run.py