Metadata-Version: 2.1
Name: Retica
Version: 1.1.2
Summary: Retica Is A Performant, Easy To Use Web Server Based On Python With HTTPS & Plugins Support.
Home-page: https://github.com/CyroCoders/Retica
Author: CyroCoders
Author-email: pypi@cyrocoders.ml
Project-URL: Bug Tracker, https://github.com/CyroCoders/Retica/issues
Classifier: Programming Language :: Python :: 3
Classifier: License :: OSI Approved :: MIT License
Classifier: Operating System :: OS Independent
Requires-Python: >=3
License-File: LICENSE
